sortdict/__init__.py
sortdict-0.0.5.dist-info/LICENSE
sortdict-0.0.5.dist-info/METADATA
sortdict-0.0.5.dist-info/WHEEL
sortdict-0.0.5.dist-info/top_level.txt
sortdict-0.0.5.dist-info/RECORD
